multicast_expert/__init__.py
multicast_expert/async_rx_socket.py
multicast_expert/interfaces.py
multicast_expert/name_to_index.py
multicast_expert/os_multicast.py
multicast_expert/py.typed
multicast_expert/rx_socket.py
multicast_expert/tx_socket.py
multicast_expert/utils.py
multicast_expert-1.6.0.dist-info/LICENSE
multicast_expert-1.6.0.dist-info/METADATA
multicast_expert-1.6.0.dist-info/WHEEL
multicast_expert-1.6.0.dist-info/RECORD
