Metadata-Version: 2.3
Name: multicast_expert
Version: 1.6.0
Summary: A library to take the fiddly parts out of multicast networking!
License: MIT
Author: Jamie Smith
Author-email: jsmith@crackofdawn.onmicrosoft.com
Requires-Python: ~=3.9
Classifier: Development Status :: 5 - Production/Stable
Classifier: Intended Audience :: Developers
Classifier: Topic :: System :: Networking
Classifier: License :: OSI Approved :: MIT License
Classifier: Programming Language :: Python :: 3
Classifier: Programming Language :: Python :: 3.9
Classifier: Programming Language :: Python :: 3.10
Classifier: Programming Language :: Python :: 3.11
Classifier: Programming Language :: Python :: 3.12
Classifier: Programming Language :: Python :: 3.13
Requires-Dist: netifaces (>=0.11.0)
Requires-Dist: typing-extensions (>=4.0.1)
Project-URL: Repository, https://github.com/multiplemonomials/multicast_expert
